brevettiai/__init__.py
brevettiai/data/__init__.py
brevettiai/data/data_generator.py
brevettiai/data/image/__init__.py
brevettiai/data/image/annotation.py
brevettiai/data/image/annotation_loader.py
brevettiai/data/image/annotation_parser.py
brevettiai/data/image/annotation_pooling.py
brevettiai/data/image/bayer_demosaic.py
brevettiai/data/image/bcimg_dataset.py
brevettiai/data/image/image_augmenter.py
brevettiai/data/image/image_loader.py
brevettiai/data/image/image_pipeline.py
brevettiai/data/image/image_processor.py
brevettiai/data/image/image_region.py
brevettiai/data/image/modules.py
brevettiai/data/image/multi_frame_imager.py
brevettiai/data/image/segmentation_loader.py
brevettiai/data/image/sequence_loader.py
brevettiai/data/image/utils.py
brevettiai/data/inspection_info.py
brevettiai/data/sample_integrity.py
brevettiai/data/sample_tools.py
brevettiai/data/serialization.py
brevettiai/data/tf_serialization.py
brevettiai/data/tf_types.py
brevettiai/data/tf_utils.py
brevettiai/datamodel/__init__.py
brevettiai/datamodel/camelmodel.py
brevettiai/datamodel/color.py
brevettiai/datamodel/dataset.py
brevettiai/datamodel/image.py
brevettiai/datamodel/image_annotation.py
brevettiai/datamodel/model_release.py
brevettiai/datamodel/tag.py
brevettiai/datamodel/web_api_types.py
brevettiai/examples/explore_application.py
brevettiai/examples/plot_annotation.py
brevettiai/examples/run_experiment.py
brevettiai/interfaces/__init__.py
brevettiai/interfaces/aws.py
brevettiai/interfaces/facets_atlas.py
brevettiai/interfaces/git_state.py
brevettiai/interfaces/package_validation.py
brevettiai/interfaces/pivot.py
brevettiai/interfaces/raygun.py
brevettiai/interfaces/remote_monitor.py
brevettiai/interfaces/sagemaker.py
brevettiai/interfaces/vue_schema_utils.py
brevettiai/io/__init__.py
brevettiai/io/cloudpath.py
brevettiai/io/credentials.py
brevettiai/io/file_cache.py
brevettiai/io/files.py
brevettiai/io/h5_metadata.py
brevettiai/io/local_io.py
brevettiai/io/minio_io.py
brevettiai-0.9.7.dist-info/METADATA
brevettiai-0.9.7.dist-info/WHEEL
brevettiai-0.9.7.dist-info/licenses/LICENSE
brevettiai-0.9.7.dist-info/RECORD
